{
	"name": "df_dim_customer_scdtype2",
	"properties": {
		"type": "MappingDataFlow",
		"typeProperties": {
			"sources": [
				{
					"dataset": {
						"referenceName": "CustomerSourceV1",
						"type": "DatasetReference"
					},
					"name": "source1"
				}
			],
			"sinks": [
				{
					"dataset": {
						"referenceName": "DimCustomerV1",
						"type": "DatasetReference"
					},
					"name": "sink1"
				}
			],
			"transformations": [
				{
					"name": "derivedColumn6"
				}
			],
			"scriptLines": [
				"source(output(",
				"          CustomerID as integer,",
				"          Title as string,",
				"          FirstName as string,",
				"          MiddleName as string,",
				"          LastName as string,",
				"          Suffix as string,",
				"          CompanyName as string,",
				"          SalesPerson as string,",
				"          EmailAddress as string,",
				"          Phone as string",
				"     ),",
				"     allowSchemaDrift: true,",
				"     validateSchema: false,",
				"     inferDriftedColumnTypes: true,",
				"     isolationLevel: 'READ_UNCOMMITTED',",
				"     format: 'table') ~> source1",
				"source1 derive(isActive = 1,",
				"          InsertedDate = currentTimestamp(),",
				"          ModifiedDate = currentTimestamp()) ~> derivedColumn6",
				"derivedColumn6 sink(allowSchemaDrift: true,",
				"     validateSchema: false,",
				"     input(",
				"          SurrKey as integer,",
				"          CustomerID as integer,",
				"          Title as string,",
				"          FirstName as string,",
				"          MiddleName as string,",
				"          LastName as string,",
				"          Suffix as string,",
				"          CompanyName as string,",
				"          SalesPerson as string,",
				"          EmailAddress as string,",
				"          Phone as string,",
				"          InsertedDate as timestamp,",
				"          ModifiedDate as timestamp,",
				"          IsActive as integer",
				"     ),",
				"     deletable:false,",
				"     insertable:true,",
				"     updateable:false,",
				"     upsertable:false,",
				"     format: 'table',",
				"     skipDuplicateMapInputs: true,",
				"     skipDuplicateMapOutputs: true,",
				"     errorHandlingOption: 'stopOnFirstError',",
				"     mapColumn(",
				"          CustomerID,",
				"          Title,",
				"          FirstName,",
				"          MiddleName,",
				"          LastName,",
				"          Suffix,",
				"          CompanyName,",
				"          SalesPerson,",
				"          EmailAddress,",
				"          Phone,",
				"          InsertedDate,",
				"          ModifiedDate,",
				"          IsActive = isActive",
				"     )) ~> sink1"
			]
		}
	}
}